winrt/_winrt_microsoft_ui_xaml_controls_primitives.cp312-win_amd64.pyd
winrt/_winrt_microsoft_ui_xaml_controls_primitives.pyi
winrt/microsoft/ui/xaml/controls/primitives/__init__.py
winrt/microsoft/ui/xaml/controls/primitives/py.typed
winrt_Microsoft.UI.Xaml.Controls.Primitives-2.3.0.dist-info/METADATA
winrt_Microsoft.UI.Xaml.Controls.Primitives-2.3.0.dist-info/WHEEL
winrt_Microsoft.UI.Xaml.Controls.Primitives-2.3.0.dist-info/top_level.txt
winrt_Microsoft.UI.Xaml.Controls.Primitives-2.3.0.dist-info/RECORD
